NMisS/SoLAE.py
NMisS/__init__.py
NMisS/approximation.py
NMisS/equations.py
NMisS/integ_diff.py
NMisS/matrix.py
NMisS/optimization.py
NMisS/spectral.py
NMisS-0.1.8.dist-info/LICENCE
NMisS-0.1.8.dist-info/METADATA
NMisS-0.1.8.dist-info/WHEEL
NMisS-0.1.8.dist-info/top_level.txt
NMisS-0.1.8.dist-info/RECORD
